jax_decision_making/__about__.py
jax_decision_making/__init__.py
jax_decision_making/decision_maker.py
jax_decision_making/posterior_handler.py
jax_decision_making/search_space.py
jax_decision_making/utility_maximizer.py
jax_decision_making/utils.py
jax_decision_making/test_functions/__init__.py
jax_decision_making/test_functions/continuous_functions.py
jax_decision_making/test_functions/non_conjugate_functions.py
jax_decision_making/utility_functions/__init__.py
jax_decision_making/utility_functions/base.py
jax_decision_making/utility_functions/expected_improvement.py
jax_decision_making/utility_functions/probability_of_improvement.py
jax_decision_making/utility_functions/thompson_sampling.py
jax_decision_making-0.0.2.dist-info/METADATA
jax_decision_making-0.0.2.dist-info/WHEEL
jax_decision_making-0.0.2.dist-info/licenses/LICENSE.txt
jax_decision_making-0.0.2.dist-info/RECORD
